aerix_certbot/__init__.py
aerix_certbot/plugin.py
aerix_certbot-0.6.2.dist-info/licenses/LICENSE
aerix_certbot-0.6.2.dist-info/METADATA
aerix_certbot-0.6.2.dist-info/WHEEL
aerix_certbot-0.6.2.dist-info/entry_points.txt
aerix_certbot-0.6.2.dist-info/top_level.txt
aerix_certbot-0.6.2.dist-info/RECORD
