Metadata-Version: 2.4
Name: aerix-certbot
Version: 0.6.2
Summary: Certbot authenticator plugin for Aerix HTTP-01 challenge responder
Author: Aerix
License: MIT
Project-URL: Homepage, https://github.com/aerix-certbot/aerix-certbot
Keywords: certbot,acme,aerix,letsencrypt,plugin
Classifier: Development Status :: 4 - Beta
Classifier: Environment :: Plugins
Classifier: Intended Audience :: System Administrators
Classifier: License :: OSI Approved :: MIT License
Classifier: Operating System :: POSIX
Classifier: Programming Language :: Python
Classifier: Programming Language :: Python :: 3
Classifier: Programming Language :: Python :: 3 :: Only
Classifier: Programming Language :: Python :: 3.8
Classifier: Programming Language :: Python :: 3.9
Classifier: Programming Language :: Python :: 3.10
Classifier: Programming Language :: Python :: 3.11
Classifier: Topic :: Internet :: WWW/HTTP
Classifier: Topic :: Security
Classifier: Topic :: System :: Systems Administration
Requires-Python: >=3.8
License-File: LICENSE
Requires-Dist: certbot>=2.7
Requires-Dist: zope.interface>=6.0
Dynamic: license-file
